img2pptx/__init__.py
img2pptx/img2pptx.py
img2pptx-0.2.2.dist-info/entry_points.txt
img2pptx-0.2.2.dist-info/WHEEL
img2pptx-0.2.2.dist-info/METADATA
img2pptx-0.2.2.dist-info/RECORD
