Metadata-Version: 2.1
Name: img2pptx
Version: 0.2.2
Summary: 
Home-page: https://github.com/MasterGowen/img-to-pptx
Author: MasterGowen
Author-email: mastergowen@gmail.com
Requires-Python: >3.7,<4.0
Classifier: Development Status :: 4 - Beta
Classifier: Environment :: Console
Classifier: Intended Audience :: Information Technology
Classifier: Programming Language :: Python :: 3
Classifier: Programming Language :: Python :: 3.10
Classifier: Programming Language :: Python :: 3.11
Classifier: Programming Language :: Python :: 3.7
Classifier: Programming Language :: Python :: 3.8
Classifier: Programming Language :: Python :: 3.9
Classifier: Topic :: Multimedia :: Graphics :: Presentation
Classifier: Topic :: Software Development :: Build Tools
Requires-Dist: click (>=8.1.3,<9.0.0)
Requires-Dist: python-pptx (>=0.6.21,<0.7.0)
Project-URL: Repository, https://github.com/MasterGowen/img-to-pptx
